webrefine/__init__.py
webrefine/_nbdev.py
webrefine/cdx.py
webrefine/core.py
webrefine/engine.py
webrefine/query.py
webrefine/runners.py
webrefine/util.py
webrefine/warc.py
webrefine-0.0.3.dist-info/LICENSE
webrefine-0.0.3.dist-info/METADATA
webrefine-0.0.3.dist-info/WHEEL
webrefine-0.0.3.dist-info/entry_points.txt
webrefine-0.0.3.dist-info/top_level.txt
webrefine-0.0.3.dist-info/RECORD
