Metadata-Version: 2.1
Name: webrefine
Version: 0.0.3
Summary: Workflow for refining datasets from World Wide Web data
Home-page: https://github.com/EdwardJRoss/webrefine/tree/master/
Author: Edward Ross
Author-email: edward@skeptric.com
License: Apache Software License 2.0
Keywords: data
Platform: UNKNOWN
Classifier: Development Status :: 3 - Alpha
Classifier: Intended Audience :: Developers
Classifier: Natural Language :: English
Classifier: Programming Language :: Python :: 3.7
Classifier: Programming Language :: Python :: 3.8
Classifier: License :: OSI Approved :: Apache Software License
Requires-Python: >=3.7
Requires-Dist: joblib
Requires-Dist: packaging
Requires-Dist: pip
Requires-Dist: requests
Requires-Dist: sqlitedict
Requires-Dist: tqdm
Requires-Dist: warcio
Provides-Extra: dev
